evolution/__init__.py
evolution/algo/__init__.py
evolution/main/AppStart.py
evolution/main/__init__.py
evolution/plugin/__init__.py
evolution/plugin/inputs/DataCleaner.py
evolution/plugin/inputs/DataExplorer.py
evolution/plugin/inputs/InputDataReader.py
evolution/plugin/inputs/__init__.py
evolution/plugin/inputs/file/FileInputDataReader.py
evolution/plugin/inputs/file/__init__.py
evolution/plugin/outputs/__init__.py
evolution/plugin/outputs/file/__init__.py
evolution/qaplugins/__init__.py
evolution/qaplugins/cleaner/QACleaner.py
evolution/qaplugins/cleaner/__init__.py
evolution/qaplugins/explorer/QADataExplorer.py
evolution/qaplugins/explorer/__init__.py
evolution/qaplugins/validator/__init__.py
nglm_i-0.1.0.dist-info/METADATA
nglm_i-0.1.0.dist-info/WHEEL
nglm_i-0.1.0.dist-info/top_level.txt
nglm_i-0.1.0.dist-info/RECORD
